{
	"name": "pl_LoopArquivos",
	"properties": {
		"description": "Pipeline responsável por ler todos os arquivos disponíveis para carga e inserir na tabela inicial da Stage.",
		"activities": [
			{
				"name": "LeituraArquivos",
				"type": "Lookup",
				"dependsOn": [],
				"policy": {
					"timeout": "7.00:00:00",
					"retry": 0,
					"retryIntervalInSeconds": 30,
					"secureOutput": false,
					"secureInput": false
				},
				"userProperties": [],
				"typeProperties": {
					"source": {
						"type": "DelimitedTextSource",
						"storeSettings": {
							"type": "AzureBlobFSReadSettings",
							"recursive": true,
							"wildcardFileName": "*",
							"enablePartitionDiscovery": false
						},
						"formatSettings": {
							"type": "DelimitedTextReadSettings"
						}
					},
					"dataset": {
						"referenceName": "Lkp_ArquivosEntrada_txt",
						"type": "DatasetReference"
					},
					"firstRowOnly": false
				}
			},
			{
				"name": "CargaArquivos",
				"description": "Loop responsável pela execução da carga de dados na tabela inicial da Stage.",
				"type": "ForEach",
				"dependsOn": [
					{
						"activity": "LeituraArquivos",
						"dependencyConditions": [
							"Succeeded"
						]
					}
				],
				"userProperties": [],
				"typeProperties": {
					"items": {
						"value": "@activity('LeituraArquivos').output.value",
						"type": "Expression"
					},
					"isSequential": false,
					"activities": [
						{
							"name": "CargaArquivosEntrada",
							"description": "Execução da carga de dados na tabela inicial da Stage, a partir de dados do ForEach",
							"type": "Copy",
							"dependsOn": [],
							"policy": {
								"timeout": "7.00:00:00",
								"retry": 0,
								"retryIntervalInSeconds": 30,
								"secureOutput": false,
								"secureInput": false
							},
							"userProperties": [],
							"typeProperties": {
								"source": {
									"type": "DelimitedTextSource",
									"storeSettings": {
										"type": "AzureBlobFSReadSettings",
										"recursive": true,
										"wildcardFileName": "*",
										"enablePartitionDiscovery": false
									},
									"formatSettings": {
										"type": "DelimitedTextReadSettings"
									}
								},
								"sink": {
									"type": "SqlServerSink"
								},
								"enableStaging": false,
								"translator": {
									"value": "@activity('LeituraArquivos').output",
									"type": "Expression"
								}
							},
							"inputs": [
								{
									"referenceName": "Cpd_ArquivosEntrada_txt",
									"type": "DatasetReference",
									"parameters": {
										"NomArquivo": {
											"value": "@item()",
											"type": "Expression"
										}
									}
								}
							],
							"outputs": [
								{
									"referenceName": "tb_ArquivosEntrada",
									"type": "DatasetReference"
								}
							]
						}
					]
				}
			}
		],
		"annotations": []
	}
}